{
  "id": "0b35ced5-d581-4bec-b6c2-d8d41aa172be",
  "prevId": "a66a476c-0e49-4f38-8eda-ec53a0092e9b",
  "version": "7",
  "dialect": "postgresql",
  "tables": {
    "public.bookings": {
      "name": "bookings",
      "schema": "",
      "columns": {
        "id": {
          "name": "id",
          "type": "uuid",
          "primaryKey": true,
          "notNull": true,
          "default": "gen_random_uuid()"
        },
        "slotId": {
          "name": "slotId",
          "type": "uuid",
          "primaryKey": false,
          "notNull": true
        },
        "studentId": {
          "name": "studentId",
          "type": "uuid",
          "primaryKey": false,
          "notNull": true
        },
        "coachId": {
          "name": "coachId",
          "type": "uuid",
          "primaryKey": false,
          "notNull": true
        },
        "createdAt": {
          "name": "createdAt",
          "type": "timestamp",
          "primaryKey": false,
          "notNull": true,
          "default": "now()"
        },
        "updatedAt": {
          "name": "updatedAt",
          "type": "timestamp",
          "primaryKey": false,
          "notNull": true,
          "default": "now()"
        }
      },
      "indexes": {},
      "foreignKeys": {},
      "compositePrimaryKeys": {},
      "uniqueConstraints": {},
      "policies": {},
      "checkConstraints": {},
      "isRLSEnabled": false
    },
    "public.records": {
      "name": "records",
      "schema": "",
      "columns": {
        "id": {
          "name": "id",
          "type": "uuid",
          "primaryKey": true,
          "notNull": true,
          "default": "gen_random_uuid()"
        },
        "bookingId": {
          "name": "bookingId",
          "type": "uuid",
          "primaryKey": false,
          "notNull": true
        },
        "coachId": {
          "name": "coachId",
          "type": "uuid",
          "primaryKey": false,
          "notNull": true
        },
        "studentId": {
          "name": "studentId",
          "type": "uuid",
          "primaryKey": false,
          "notNull": true
        },
        "satisfactionScore": {
          "name": "satisfactionScore",
          "type": "integer",
          "primaryKey": false,
          "notNull": true
        },
        "notes": {
          "name": "notes",
          "type": "text",
          "primaryKey": false,
          "notNull": true
        },
        "createdAt": {
          "name": "createdAt",
          "type": "timestamp",
          "primaryKey": false,
          "notNull": true,
          "default": "now()"
        },
        "updatedAt": {
          "name": "updatedAt",
          "type": "timestamp",
          "primaryKey": false,
          "notNull": true,
          "default": "now()"
        }
      },
      "indexes": {},
      "foreignKeys": {},
      "compositePrimaryKeys": {},
      "uniqueConstraints": {},
      "policies": {},
      "checkConstraints": {},
      "isRLSEnabled": false
    },
    "public.scheduleAvailabilities": {
      "name": "scheduleAvailabilities",
      "schema": "",
      "columns": {
        "id": {
          "name": "id",
          "type": "uuid",
          "primaryKey": true,
          "notNull": true,
          "default": "gen_random_uuid()"
        },
        "scheduleId": {
          "name": "scheduleId",
          "type": "uuid",
          "primaryKey": false,
          "notNull": true
        },
        "startTime": {
          "name": "startTime",
          "type": "text",
          "primaryKey": false,
          "notNull": true
        },
        "endTime": {
          "name": "endTime",
          "type": "text",
          "primaryKey": false,
          "notNull": true
        },
        "dayOfWeek": {
          "name": "dayOfWeek",
          "type": "day",
          "typeSchema": "public",
          "primaryKey": false,
          "notNull": true
        }
      },
      "indexes": {
        "scheduleIdIndex": {
          "name": "scheduleIdIndex",
          "columns": [
            {
              "expression": "scheduleId",
              "isExpression": false,
              "asc": true,
              "nulls": "last"
            }
          ],
          "isUnique": false,
          "concurrently": false,
          "method": "btree",
          "with": {}
        }
      },
      "foreignKeys": {
        "scheduleAvailabilities_scheduleId_schedules_id_fk": {
          "name": "scheduleAvailabilities_scheduleId_schedules_id_fk",
          "tableFrom": "scheduleAvailabilities",
          "tableTo": "schedules",
          "columnsFrom": [
            "scheduleId"
          ],
          "columnsTo": [
            "id"
          ],
          "onDelete": "cascade",
          "onUpdate": "no action"
        }
      },
      "compositePrimaryKeys": {},
      "uniqueConstraints": {},
      "policies": {},
      "checkConstraints": {},
      "isRLSEnabled": false
    },
    "public.schedules": {
      "name": "schedules",
      "schema": "",
      "columns": {
        "id": {
          "name": "id",
          "type": "uuid",
          "primaryKey": true,
          "notNull": true,
          "default": "gen_random_uuid()"
        },
        "timezone": {
          "name": "timezone",
          "type": "text",
          "primaryKey": false,
          "notNull": true
        },
        "coachId": {
          "name": "coachId",
          "type": "uuid",
          "primaryKey": false,
          "notNull": true
        },
        "createdAt": {
          "name": "createdAt",
          "type": "timestamp",
          "primaryKey": false,
          "notNull": true,
          "default": "now()"
        },
        "updatedAt": {
          "name": "updatedAt",
          "type": "timestamp",
          "primaryKey": false,
          "notNull": true,
          "default": "now()"
        }
      },
      "indexes": {
        "unique_coach_id": {
          "name": "unique_coach_id",
          "columns": [
            {
              "expression": "coachId",
              "isExpression": false,
              "asc": true,
              "nulls": "last"
            }
          ],
          "isUnique": true,
          "concurrently": false,
          "method": "btree",
          "with": {}
        }
      },
      "foreignKeys": {},
      "compositePrimaryKeys": {},
      "uniqueConstraints": {},
      "policies": {},
      "checkConstraints": {},
      "isRLSEnabled": false
    },
    "public.slots": {
      "name": "slots",
      "schema": "",
      "columns": {
        "id": {
          "name": "id",
          "type": "uuid",
          "primaryKey": true,
          "notNull": true,
          "default": "gen_random_uuid()"
        },
        "name": {
          "name": "name",
          "type": "text",
          "primaryKey": false,
          "notNull": true
        },
        "coachId": {
          "name": "coachId",
          "type": "uuid",
          "primaryKey": false,
          "notNull": true
        },
        "durationInMinutes": {
          "name": "durationInMinutes",
          "type": "integer",
          "primaryKey": false,
          "notNull": true
        },
        "createdAt": {
          "name": "createdAt",
          "type": "timestamp",
          "primaryKey": false,
          "notNull": true,
          "default": "now()"
        },
        "updatedAt": {
          "name": "updatedAt",
          "type": "timestamp",
          "primaryKey": false,
          "notNull": true,
          "default": "now()"
        }
      },
      "indexes": {},
      "foreignKeys": {},
      "compositePrimaryKeys": {},
      "uniqueConstraints": {},
      "policies": {},
      "checkConstraints": {},
      "isRLSEnabled": false
    },
    "public.users": {
      "name": "users",
      "schema": "",
      "columns": {
        "id": {
          "name": "id",
          "type": "uuid",
          "primaryKey": true,
          "notNull": true,
          "default": "gen_random_uuid()"
        },
        "name": {
          "name": "name",
          "type": "text",
          "primaryKey": false,
          "notNull": true
        },
        "role": {
          "name": "role",
          "type": "text",
          "primaryKey": false,
          "notNull": true
        },
        "phoneNmber": {
          "name": "phoneNmber",
          "type": "text",
          "primaryKey": false,
          "notNull": true
        },
        "createdAt": {
          "name": "createdAt",
          "type": "timestamp",
          "primaryKey": false,
          "notNull": true,
          "default": "now()"
        },
        "updatedAt": {
          "name": "updatedAt",
          "type": "timestamp",
          "primaryKey": false,
          "notNull": true,
          "default": "now()"
        }
      },
      "indexes": {},
      "foreignKeys": {},
      "compositePrimaryKeys": {},
      "uniqueConstraints": {},
      "policies": {},
      "checkConstraints": {},
      "isRLSEnabled": false
    }
  },
  "enums": {
    "public.day": {
      "name": "day",
      "schema": "public",
      "values": [
        "monday",
        "tuesday",
        "wednesday",
        "thursday",
        "friday",
        "saturday",
        "sunday"
      ]
    }
  },
  "schemas": {},
  "sequences": {},
  "roles": {},
  "policies": {},
  "views": {},
  "_meta": {
    "columns": {},
    "schemas": {},
    "tables": {}
  }
}